{"data": [
{"date":"1/7/2018","dial": "4365"},
{"date":"1/14/2018","dial": "4374"},
{"date":"1/21/2018","dial": "4381"},
{"date":"1/28/2018","dial": "4389"},
{"date":"2/3/2018","dial": "4399"},
{"date":"2/11/2018","dial": "4416"},
{"date":"2/18/2018","dial": "4437"},
{"date":"2/24/2018","dial": "4450"},
{"date":"3/3/2018","dial": "4473"},
{"date":"3/10/2018","dial": "4497"},
{"date":"3/17/2018","dial": "4530"},
{"date":"3/24/2018","dial": "4563"},
{"date":"3/31/2018","dial": "4596"},
{"date":"4/8/2018","dial": "4632"},
{"date":"4/14/2018","dial": "4665"},
{"date":"4/21/2018","dial": "4713"},
{"date":"4/28/2018","dial": "4789"},
{"date":"5/4/2018","dial": "4846"},
{"date":"5/13/2018","dial": "4919"},
{"date":"5/19/2018","dial": "4982"},
{"date":"5/26/2018","dial": "5051"},
{"date":"6/9/2018","dial": "5204"},
{"date":"6/16/2018","dial": "5266"},
{"date":"6/24/2018","dial": "5369"},
{"date":"7/1/2018","dial": "5473"},
{"date":"7/7/2018","dial": "5544"},
{"date":"7/15/2018","dial": "5641"},
{"date":"7/22/2018","dial": "5730"},
{"date":"8/4/2018","dial": "5896"},
{"date":"8/12/2018","dial": "5971"},
{"date":"8/18/2018","dial": "6030"}
]}